XtraMLTools/Classification.py
XtraMLTools/Preprocessing.py
XtraMLTools/Regression.py
XtraMLTools/__init__.py
XtraMLTools-0.1.2.dist-info/LICENSE.txt
XtraMLTools-0.1.2.dist-info/METADATA
XtraMLTools-0.1.2.dist-info/WHEEL
XtraMLTools-0.1.2.dist-info/top_level.txt
XtraMLTools-0.1.2.dist-info/RECORD
