Metadata-Version: 2.1
Name: XtraMLTools
Version: 0.1.2
Summary: Additional Tools for Machine Learning
Author: Andrew Douglas
Classifier: Programming Language :: Python :: 3
Classifier: License :: OSI Approved :: MIT License
License-File: LICENSE.txt
Requires-Dist: numpy
Requires-Dist: pandas
Requires-Dist: scipy
Requires-Dist: scikit-learn
Requires-Dist: xgboost
Requires-Dist: matplotlib
